{
  "hints": [],
  "groups": [
    {
      "sourceType": "com.lzh.game.repository.GameRepositoryConfig",
      "name": "game.repository",
      "type": "com.lzh.game.repository.GameRepositoryConfig"
    }
  ],
  "properties": [
    {
      "sourceType": "com.lzh.game.repository.GameRepositoryConfig",
      "defaultValue": true,
      "name": "game.repository.clear-redis-after-close",
      "type": "java.lang.Boolean"
    },
    {
      "sourceType": "com.lzh.game.repository.GameRepositoryConfig",
      "defaultValue": 5,
      "name": "game.repository.consume-interval-time",
      "description": "Use {@link com.lzh.game.repository.db.persist.LocationMemoryPersistQueue} each {@link #consumeIntervalTime } will consume queue",
      "type": "java.lang.Long"
    },
    {
      "sourceType": "com.lzh.game.repository.GameRepositoryConfig",
      "defaultValue": "persist_queue",
      "name": "game.repository.redis-persist-top",
      "description": "Use {@link com.lzh.game.repository.db.persist.RedisPersistConsumer}",
      "type": "java.lang.String"
    }
  ]
}